lightkube/models/__init__.py
lightkube/models/_schema.py
lightkube/models/admissionregistration_v1.py
lightkube/models/admissionregistration_v1alpha1.py
lightkube/models/admissionregistration_v1beta1.py
lightkube/models/apiextensions_v1.py
lightkube/models/apiregistration_v1.py
lightkube/models/apiserverinternal_v1alpha1.py
lightkube/models/apps_v1.py
lightkube/models/authentication_v1.py
lightkube/models/authorization_v1.py
lightkube/models/autoscaling_v1.py
lightkube/models/autoscaling_v2.py
lightkube/models/batch_v1.py
lightkube/models/certificates_v1.py
lightkube/models/certificates_v1alpha1.py
lightkube/models/certificates_v1beta1.py
lightkube/models/coordination_v1.py
lightkube/models/coordination_v1alpha2.py
lightkube/models/coordination_v1beta1.py
lightkube/models/core_v1.py
lightkube/models/discovery_v1.py
lightkube/models/events_v1.py
lightkube/models/flowcontrol_v1.py
lightkube/models/meta_v1.py
lightkube/models/networking_v1.py
lightkube/models/networking_v1beta1.py
lightkube/models/node_v1.py
lightkube/models/policy_v1.py
lightkube/models/rbac_v1.py
lightkube/models/resource.py
lightkube/models/resource_v1.py
lightkube/models/resource_v1alpha3.py
lightkube/models/resource_v1beta1.py
lightkube/models/resource_v1beta2.py
lightkube/models/runtime.py
lightkube/models/scheduling_v1.py
lightkube/models/scheduling_v1alpha1.py
lightkube/models/storage_v1.py
lightkube/models/storage_v1beta1.py
lightkube/models/storagemigration_v1beta1.py
lightkube/models/util_intstr.py
lightkube/models/version.py
lightkube/resources/__init__.py
lightkube/resources/admissionregistration_v1.py
lightkube/resources/admissionregistration_v1alpha1.py
lightkube/resources/admissionregistration_v1beta1.py
lightkube/resources/apiextensions_v1.py
lightkube/resources/apiregistration_v1.py
lightkube/resources/apps_v1.py
lightkube/resources/authentication_v1.py
lightkube/resources/authorization_v1.py
lightkube/resources/autoscaling_v1.py
lightkube/resources/autoscaling_v2.py
lightkube_models-1.35.0.8.dist-info/METADATA
lightkube_models-1.35.0.8.dist-info/WHEEL
lightkube_models-1.35.0.8.dist-info/entry_points.txt
lightkube_models-1.35.0.8.dist-info/licenses/LICENSE
lightkube_models-1.35.0.8.dist-info/RECORD
